examples/__init__.py
examples/bench_large_hyperspectral.py
examples/bench_large_hyperspectral.pyi
examples/demo_kwcoco_spaces.py
examples/demo_sql_and_zip_files.py
examples/draw_gt_and_predicted_boxes.py
examples/draw_gt_and_predicted_boxes.pyi
examples/example_sar_and_msi.py
examples/faq.py
examples/faq.pyi
examples/getting_started_existing_dataset.py
examples/getting_started_existing_dataset.pyi
examples/image_access.py
examples/loading_multispectral_data.py
examples/loading_multispectral_data.pyi
examples/loop_over_frame_annotations.py
examples/modification_example.py
examples/modification_example.pyi
examples/shifting_annots.py
examples/shifting_annots.pyi
examples/simple_kwcoco_torch_dataset.py
examples/simple_kwcoco_torch_dataset.pyi
examples/vectorized_interface.py
examples/vectorized_interface.pyi
kwcoco/__init__.py
kwcoco/__main__.py
kwcoco/__main__.pyi
kwcoco/_helpers.py
kwcoco/_helpers.pyi
kwcoco/abstract_coco_dataset.py
kwcoco/abstract_coco_dataset.pyi
kwcoco/category_tree.py
kwcoco/category_tree.pyi
kwcoco/channel_spec.py
kwcoco/channel_spec.pyi
kwcoco/coco_dataset.py
kwcoco/coco_dataset.pyi
kwcoco/coco_evaluator.py
kwcoco/coco_evaluator.pyi
kwcoco/coco_image.py
kwcoco/coco_image.pyi
kwcoco/coco_objects1d.py
kwcoco/coco_objects1d.pyi
kwcoco/coco_schema.py
kwcoco/coco_schema.pyi
kwcoco/coco_sql_dataset.py
kwcoco/coco_sql_dataset.pyi
kwcoco/compat_dataset.py
kwcoco/compat_dataset.pyi
kwcoco/exceptions.py
kwcoco/exceptions.pyi
kwcoco/kpf.py
kwcoco/kw18.py
kwcoco/py.typed
kwcoco/sensorchan_spec.py
kwcoco/sensorchan_spec.pyi
kwcoco/cli/__init__.py
kwcoco/cli/__main__.py
kwcoco/cli/coco_conform.py
kwcoco/cli/coco_eval.py
kwcoco/cli/coco_fixup.py
kwcoco/cli/coco_grab.py
kwcoco/cli/coco_info.py
kwcoco/cli/coco_modify_categories.py
kwcoco/cli/coco_move.py
kwcoco/cli/coco_move_assets.py
kwcoco/cli/coco_plot_stats.py
kwcoco/cli/coco_reroot.py
kwcoco/cli/coco_show.py
kwcoco/cli/coco_split.py
kwcoco/cli/coco_stats.py
kwcoco/cli/coco_subset.py
kwcoco-0.8.8.dist-info/licenses/LICENSE
kwcoco-0.8.8.dist-info/METADATA
kwcoco-0.8.8.dist-info/WHEEL
kwcoco-0.8.8.dist-info/entry_points.txt
kwcoco-0.8.8.dist-info/top_level.txt
kwcoco-0.8.8.dist-info/RECORD
